stockcodes/__init__.py
stockcodes/stockcodes.py
stockcodes-0.0.4.dist-info/LICENSE
stockcodes-0.0.4.dist-info/METADATA
stockcodes-0.0.4.dist-info/WHEEL
stockcodes-0.0.4.dist-info/top_level.txt
stockcodes-0.0.4.dist-info/RECORD
